{"engine_id": 13, "values": [{"feature": "tr_s21_slope5", "shap_value": 0.13510078384230534}, {"feature": "rs_s2_rmin5", "shap_value": 0.10523479767143726}, {"feature": "sensor_measurement_12_kalman", "shap_value": -0.08515945539499323}, {"feature": "rc_s12_pct1", "shap_value": -0.08483045150836309}, {"feature": "sensor_measurement_20_kalman", "shap_value": -0.08096580968316024}, {"feature": "rs_s12_rmin5", "shap_value": -0.07954806881025434}, {"feature": "rc_s21_pct1", "shap_value": 0.06672836023693283}, {"feature": "rs_s13_rmin5", "shap_value": -0.06670686323971799}, {"feature": "tr_s15_slope5", "shap_value": -0.0666428445527951}, {"feature": "rc_s4_pct1", "shap_value": -0.06523776780813932}, {"feature": "tr_s7_slope5", "shap_value": -0.05571551967101793}, {"feature": "si_s7_s11_ratio", "shap_value": 0.0537808111247917}, {"feature": "sensor_measurement_13_kalman", "shap_value": 0.05345225108224743}, {"feature": "rc_s9_pct1", "shap_value": 0.05285577628140648}, {"feature": "si_s11_s12_prod", "shap_value": 0.04830709050196068}, {"feature": "tr_s9_slope5", "shap_value": 0.04683538352449735}, {"feature": "sensor_measurement_4_kalman", "shap_value": -0.04450154535782834}, {"feature": "sensor_measurement_7_kalman", "shap_value": 0.043294472713023426}, {"feature": "tr_s12_slope5", "shap_value": -0.04205014396769305}, {"feature": "sensor_measurement_2_kalman", "shap_value": 0.0416176937520504}, {"feature": "rs_s9_rmin5", "shap_value": 0.04159414853202179}, {"feature": "operational_setting_1", "shap_value": 0.04145808309161415}, {"feature": "rc_s7_pct1", "shap_value": -0.04115461409091949}, {"feature": "sensor_measurement_15_kalman", "shap_value": -0.0331097139356037}, {"feature": "si_s4_s12_prod", "shap_value": 0.032742801296990365}, {"feature": "sensor_measurement_17_kalman", "shap_value": 0.03234309434968357}, {"feature": "operational_setting_2", "shap_value": -0.02945887732009093}, {"feature": "si_s11_s12_ratio", "shap_value": -0.029055620760967335}, {"feature": "tr_s4_slope5", "shap_value": -0.028175869044692565}, {"feature": "rc_s2_pct1", "shap_value": 0.02722771850725015}, {"feature": "rc_s13_pct1", "shap_value": -0.026851305466455717}, {"feature": "rs_s3_rmin5", "shap_value": -0.02623816916505651}, {"feature": "sensor_measurement_21_kalman", "shap_value": -0.023386392944181957}, {"feature": "tr_s2_slope5", "shap_value": -0.023237988290687402}, {"feature": "si_s12_s21_prod", "shap_value": 0.02014315005702277}, {"feature": "rc_s20_pct1", "shap_value": 0.01926901681969563}, {"feature": "rc_s17_pct1", "shap_value": -0.01891181212461864}, {"feature": "tr_s13_slope5", "shap_value": 0.018758341018110514}, {"feature": "tr_s20_slope5", "shap_value": 0.018509487396416564}, {"feature": "rs_s11_rmin5", "shap_value": 0.018393360290307706}, {"feature": "rc_s15_pct1", "shap_value": -0.01782046929001808}, {"feature": "si_s4_s11_prod", "shap_value": 0.017212092907478414}, {"feature": "si_s4_s11_ratio", "shap_value": -0.016889457032084464}, {"feature": "rs_s20_rmin5", "shap_value": 0.016807031498926032}, {"feature": "rs_s21_rmin5", "shap_value": -0.01668162758772572}, {"feature": "rs_s8_rmin5", "shap_value": -0.015985396023218832}, {"feature": "sensor_measurement_9_kalman", "shap_value": -0.013794803218722033}, {"feature": "rc_s11_pct1", "shap_value": -0.013366483916373302}, {"feature": "si_s7_s11_prod", "shap_value": 0.013337339191154266}, {"feature": "rs_s17_rmin5", "shap_value": -0.012932744561112486}, {"feature": "si_s12_s21_ratio", "shap_value": 0.012563675812756022}, {"feature": "tr_s8_slope5", "shap_value": -0.011649155151098966}, {"feature": "sensor_measurement_11_kalman", "shap_value": -0.009902709296632868}, {"feature": "tr_s17_slope5", "shap_value": -0.008619734093857308}, {"feature": "sensor_measurement_8_kalman", "shap_value": 0.008194513424494213}, {"feature": "rs_s7_rmin5", "shap_value": -0.008116046191814046}, {"feature": "tr_s3_slope5", "shap_value": -0.007978107252468666}, {"feature": "rc_s8_pct1", "shap_value": 0.0075348565044502415}, {"feature": "si_s4_s2_prod", "shap_value": 0.006948087911587209}, {"feature": "rc_s3_pct1", "shap_value": 0.005967159755527973}, {"feature": "si_s4_s12_ratio", "shap_value": -0.005941164227745806}, {"feature": "si_s4_s2_ratio", "shap_value": 0.004803274441170894}, {"feature": "rs_s15_rmin5", "shap_value": 0.002909929106438843}, {"feature": "rs_s4_rmin5", "shap_value": -0.002286382904276252}, {"feature": "sensor_measurement_3_kalman", "shap_value": 0.0014797811900886396}, {"feature": "tr_s11_slope5", "shap_value": 0.0011766715596119562}]}